pystitch/A100Reader.py
pystitch/A10oReader.py
pystitch/ArtReader.py
pystitch/BroReader.py
pystitch/ColReader.py
pystitch/ColWriter.py
pystitch/CsvReader.py
pystitch/CsvWriter.py
pystitch/DatReader.py
pystitch/DsbReader.py
pystitch/DstReader.py
pystitch/DstWriter.py
pystitch/DszReader.py
pystitch/EdrReader.py
pystitch/EdrWriter.py
pystitch/EmbCompress.py
pystitch/EmbConstant.py
pystitch/EmbEncoder.py
pystitch/EmbFunctions.py
pystitch/EmbMatrix.py
pystitch/EmbPattern.py
pystitch/EmbThread.py
pystitch/EmbThreadHus.py
pystitch/EmbThreadJef.py
pystitch/EmbThreadPec.py
pystitch/EmbThreadSew.py
pystitch/EmbThreadShv.py
pystitch/EmdReader.py
pystitch/ExpReader.py
pystitch/ExpWriter.py
pystitch/ExyReader.py
pystitch/FxyReader.py
pystitch/GcodeReader.py
pystitch/GcodeWriter.py
pystitch/GenericWriter.py
pystitch/GtReader.py
pystitch/HusReader.py
pystitch/InbReader.py
pystitch/InfReader.py
pystitch/InfWriter.py
pystitch/InkstitchGcodeWriter.py
pystitch/IqpReader.py
pystitch/JefReader.py
pystitch/JefWriter.py
pystitch/JpxReader.py
pystitch/JsonReader.py
pystitch/JsonWriter.py
pystitch/KsmReader.py
pystitch/MaxReader.py
pystitch/MitReader.py
pystitch/NewReader.py
pystitch/PcdReader.py
pystitch/PcmReader.py
pystitch/PcqReader.py
pystitch/PcsReader.py
pystitch/PecGraphics.py
pystitch/PecReader.py
pystitch/PecWriter.py
pystitch/PesReader.py
pystitch/PesWriter.py
pystitch/PhbReader.py
pystitch/PhcReader.py
pystitch/PltReader.py
pystitch/PltWriter.py
pystitch/PmvReader.py
pystitch/PmvWriter.py
pystitch/PngWriter.py
pystitch/QccReader.py
pystitch/QccWriter.py
pystitch/ReadHelper.py
pystitch/SewReader.py
pystitch/ShvReader.py
pystitch/SpxReader.py
pystitch/StcReader.py
pystitch/StxReader.py
pystitch/SvgWriter.py
pystitch/TapReader.py
pystitch/TbfReader.py
pystitch/TbfWriter.py
pystitch/TxtWriter.py
pystitch/U01Reader.py
pystitch/U01Writer.py
pystitch/Vp3Reader.py
pystitch/Vp3Writer.py
pystitch/WriteHelper.py
pystitch/XxxReader.py
pystitch/XxxWriter.py
pystitch/ZhsReader.py
pystitch-1.0.0.dist-info/licenses/LICENSE
pystitch-1.0.0.dist-info/METADATA
pystitch-1.0.0.dist-info/WHEEL
pystitch-1.0.0.dist-info/top_level.txt
pystitch-1.0.0.dist-info/RECORD
