Metadata-Version: 2.4
Name: pystitch
Version: 1.0.0
Summary: Embroidery IO library
Author: Tatarize
Maintainer: Kaalleen
License-Expression: MIT
Project-URL: Repository, https://github.com/inkstitch/pystitch
Project-URL: Issues, https://github.com/inkstitch/pystitch/issues
Keywords: embroidery,file conversion
Classifier: Development Status :: 5 - Production/Stable
Classifier: Intended Audience :: Developers
Classifier: Programming Language :: Python :: 3.9
Classifier: Programming Language :: Python :: 3.10
Classifier: Programming Language :: Python :: 3.11
Classifier: Programming Language :: Python :: 3.12
Classifier: Programming Language :: Python :: 3.13
Classifier: Operating System :: OS Independent
Classifier: Topic :: Software Development :: Libraries :: Python Modules
Requires-Python: >=3.9
License-File: LICENSE
Dynamic: license-file
